tdvrptw_snrpga2/__init__.py
tdvrptw_snrpga2/compute_inputs.py
tdvrptw_snrpga2/genetic_alg.py
tdvrptw_snrpga2/genetic_op.py
tdvrptw_snrpga2/main.py
tdvrptw_snrpga2/tdvrptw_instance.py
tdvrptw_snrpga2/utils.py
tdvrptw_snrpga2/src/__init__.py
tdvrptw_snrpga2/src/compute_inputs.py
tdvrptw_snrpga2/src/genetic_alg.py
tdvrptw_snrpga2/src/genetic_op.py
tdvrptw_snrpga2/src/utils.py
tdvrptw_snrpga2/test/__init__.py
tdvrptw_snrpga2/test/cases.py
tdvrptw_snrpga2/test/test_compute_inputs.py
tdvrptw_snrpga2/test/test_genetic_alg.py
tdvrptw_snrpga2/test/test_genetic_op.py
tdvrptw_snrpga2-0.2.1.dist-info/METADATA
tdvrptw_snrpga2-0.2.1.dist-info/WHEEL
tdvrptw_snrpga2-0.2.1.dist-info/top_level.txt
tdvrptw_snrpga2-0.2.1.dist-info/RECORD
