Metadata-Version: 2.1
Name: tdvrptw-snrpga2
Version: 0.2.1
Summary: SNRPGA2 algorithm to solve TDVRPTW
Home-page: UNKNOWN
Author: Yingchen Ma
Author-email: ericma@comcast.net
License: UNKNOWN
Keywords: python,tdvrptw,vrp,tdvrp,vrptw
Platform: UNKNOWN
Classifier: Development Status :: 3 - Alpha
Classifier: Intended Audience :: Education
Classifier: Programming Language :: Python :: 3
Classifier: Operating System :: MacOS :: MacOS X
Classifier: Operating System :: Microsoft :: Windows
Requires-Dist: numpy
Requires-Dist: scipy
Requires-Dist: tqdm
